LICENSE
MANIFEST.in
README.md
setup.py
isitup/__init__.py
isitup/cli.py
isitup/main.py
isitup.egg-info/PKG-INFO
isitup.egg-info/SOURCES.txt
isitup.egg-info/dependency_links.txt
isitup.egg-info/entry_points.txt
isitup.egg-info/requires.txt
isitup.egg-info/top_level.txt